dxlib/__init__.py
dxlib/benchmark.py
dxlib/common.py
dxlib/module_proxy.py
dxlib/types.py
dxlib/core/__init__.py
dxlib/core/formatter.py
dxlib/core/manager.py
dxlib/core/portfolio.py
dxlib/core/signal.py
dxlib/core/dynamics/__init__.py
dxlib/core/dynamics/cox_ingersoll_ross.py
dxlib/core/dynamics/geometric_brownian_motion.py
dxlib/core/dynamics/hawkes.py
dxlib/core/dynamics/ohrnstein_uhlenbeck.py
dxlib/core/dynamics/stochastic_process.py
dxlib/core/indicators/__init__.py
dxlib/core/indicators/bollinger_bands.py
dxlib/core/indicators/rsi.py
dxlib/core/indicators/filters/__init__.py
dxlib/core/indicators/filters/momentum.py
dxlib/core/indicators/filters/reversion.py
dxlib/core/indicators/filters/volatility.py
dxlib/core/instruments/__init__.py
dxlib/core/instruments/instrument.py
dxlib/core/instruments/instrument_store.py
dxlib/core/instruments/universe.py
dxlib/data/__init__.py
dxlib/data/hdf.py
dxlib/data/registry.py
dxlib/data/serializable.py
dxlib/data/storage.py
dxlib/data/dtos/__init__.py
dxlib/data/dtos/dto.py
dxlib/data/dtos/history_dto.py
dxlib/data/dtos/instrument_dto.py
dxlib/history/__init__.py
dxlib/history/bar.py
dxlib/history/dtype_validation.py
dxlib/history/history.py
dxlib/history/history_schema.py
dxlib/history/history_view.py
dxlib/interfaces/__init__.py
dxlib/interfaces/account_interface.py
dxlib/interfaces/interface.py
dxlib/interfaces/market_interface.py
dxlib/interfaces/order_interface.py
dxlib/interfaces/trading_interface.py
dxlib/interfaces/external/__init__.py
dxlib/interfaces/external/utils.py
dxlib/interfaces/external/cboe/__init__.py
dxlib/interfaces/external/cboe/cboe.py
dxlib/interfaces/external/ibkr/__init__.py
dxlib/interfaces/external/ibkr/ibkr.py
dxlib/interfaces/external/ibkr/ibkr_account.py
dxlib/interfaces/external/ibkr/ibkr_market.py
dxlib/interfaces/external/ibkr/position.py
dxlib/interfaces/external/ibkr/requirements.txt
dxlib/interfaces/external/ibkr/wrapper.py
dxlib/interfaces/external/investing_com/__init__.py
dxlib-2.1.0.dist-info/licenses/LICENSE
dxlib-2.1.0.dist-info/METADATA
dxlib-2.1.0.dist-info/WHEEL
dxlib-2.1.0.dist-info/top_level.txt
dxlib-2.1.0.dist-info/RECORD
