Metadata-Version: 2.4
Name: dxlib
Version: 2.1.0
Summary: A library for quantitative finance, with tools for data handling, network interfacing, and mathematical modeling.
Author-email: Rafael Zimmer <rzimmerdev@gmail.com>
License-Expression: MIT
Project-URL: homepage, https://github.com/divergex/dxlib
Classifier: Programming Language :: Python :: 3
Classifier: Operating System :: OS Independent
Requires-Python: >=3.10
License-File: LICENSE
Requires-Dist: cloudscraper~=1.2.71
Requires-Dist: fastapi~=0.116.1
Requires-Dist: h5py~=3.14.0
Requires-Dist: httpx~=0.28.1
Requires-Dist: ibapi~=9.81.1.post1
Requires-Dist: lxml>=6.0.0
Requires-Dist: matplotlib~=3.9.4
Requires-Dist: numpy~=2.1.3
Requires-Dist: pandas~=2.2.2
Requires-Dist: pandas-stubs>=2.3.0.250703
Requires-Dist: pydantic~=2.11.5
Requires-Dist: requests~=2.32.3
Requires-Dist: scipy~=1.15.1
Requires-Dist: starlette~=0.47.2
Requires-Dist: statsmodels~=0.14.4
Requires-Dist: uvicorn~=0.34.0
Dynamic: license-file
